{
    "Ar36": {
        "error": 0.0001599797388800471,
        "fit": "Bracketing Interpolate",
        "references": [
            {
                "exclude": "ok",
                "record_id": "bu-FD-F-467",
                "uuid": "2a56935c-e9b7-4223-856e-456dd21aefe0"
            },
            {
                "exclude": "ok",
                "record_id": "bu-FD-F-468",
                "uuid": "f67658d0-2729-45a1-8c6b-8b31382c1a7c"
            },
            {
                "exclude": "ok",
                "record_id": "bu-FD-F-469",
                "uuid": "e212c0f9-6b16-487f-a4df-4ac402a68210"
            },
            {
                "exclude": "ok",
                "record_id": "bu-FD-F-470",
                "uuid": "4c4cb15d-030c-436a-8d24-2b7d9c38557f"
            },
            {
                "exclude": "ok",
                "record_id": "bu-FD-F-471",
                "uuid": "a29c3368-bfa4-4f29-b388-2aad63a78386"
            },
            {
                "exclude": "ok",
                "record_id": "bu-FD-F-472",
                "uuid": "4e8f2cde-58c0-4063-9f50-027292e9d391"
            },
            {
                "exclude": "ok",
                "record_id": "bu-FD-F-473",
                "uuid": "d6ba530d-4266-4f27-897d-d2ce86f8a8d6"
            },
            {
                "exclude": "ok",
                "record_id": "bu-FD-F-474",
                "uuid": "90d7ea7e-35f7-4aee-8d66-4bcb61efd3b3"
            }
        ],
        "reviewed": true,
        "value": 0.002571763463287474
    },
    "Ar37": {
        "error": 0.010182876332696036,
        "fit": "Bracketing Interpolate",
        "references": [
            {
                "exclude": "ok",
                "record_id": "bu-FD-F-467",
                "uuid": "2a56935c-e9b7-4223-856e-456dd21aefe0"
            },
            {
                "exclude": "ok",
                "record_id": "bu-FD-F-468",
                "uuid": "f67658d0-2729-45a1-8c6b-8b31382c1a7c"
            },
            {
                "exclude": "ok",
                "record_id": "bu-FD-F-469",
                "uuid": "e212c0f9-6b16-487f-a4df-4ac402a68210"
            },
            {
                "exclude": "ok",
                "record_id": "bu-FD-F-470",
                "uuid": "4c4cb15d-030c-436a-8d24-2b7d9c38557f"
            },
            {
                "exclude": "ok",
                "record_id": "bu-FD-F-471",
                "uuid": "a29c3368-bfa4-4f29-b388-2aad63a78386"
            },
            {
                "exclude": "ok",
                "record_id": "bu-FD-F-472",
                "uuid": "4e8f2cde-58c0-4063-9f50-027292e9d391"
            },
            {
                "exclude": "ok",
                "record_id": "bu-FD-F-473",
                "uuid": "d6ba530d-4266-4f27-897d-d2ce86f8a8d6"
            },
            {
                "exclude": "ok",
                "record_id": "bu-FD-F-474",
                "uuid": "90d7ea7e-35f7-4aee-8d66-4bcb61efd3b3"
            }
        ],
        "reviewed": true,
        "value": -0.021920783494704527
    },
    "Ar38": {
        "error": 0.011953201525852386,
        "fit": "Bracketing Interpolate",
        "references": [
            {
                "exclude": "ok",
                "record_id": "bu-FD-F-467",
                "uuid": "2a56935c-e9b7-4223-856e-456dd21aefe0"
            },
            {
                "exclude": "ok",
                "record_id": "bu-FD-F-468",
                "uuid": "f67658d0-2729-45a1-8c6b-8b31382c1a7c"
            },
            {
                "exclude": "ok",
                "record_id": "bu-FD-F-469",
                "uuid": "e212c0f9-6b16-487f-a4df-4ac402a68210"
            },
            {
                "exclude": "ok",
                "record_id": "bu-FD-F-470",
                "uuid": "4c4cb15d-030c-436a-8d24-2b7d9c38557f"
            },
            {
                "exclude": "ok",
                "record_id": "bu-FD-F-471",
                "uuid": "a29c3368-bfa4-4f29-b388-2aad63a78386"
            },
            {
                "exclude": "ok",
                "record_id": "bu-FD-F-472",
                "uuid": "4e8f2cde-58c0-4063-9f50-027292e9d391"
            },
            {
                "exclude": "ok",
                "record_id": "bu-FD-F-473",
                "uuid": "d6ba530d-4266-4f27-897d-d2ce86f8a8d6"
            },
            {
                "exclude": "ok",
                "record_id": "bu-FD-F-474",
                "uuid": "90d7ea7e-35f7-4aee-8d66-4bcb61efd3b3"
            }
        ],
        "reviewed": true,
        "value": -0.01322247069638434
    },
    "Ar39": {
        "error": 0.022248044701971004,
        "fit": "Bracketing Interpolate",
        "references": [
            {
                "exclude": "ok",
                "record_id": "bu-FD-F-467",
                "uuid": "2a56935c-e9b7-4223-856e-456dd21aefe0"
            },
            {
                "exclude": "ok",
                "record_id": "bu-FD-F-468",
                "uuid": "f67658d0-2729-45a1-8c6b-8b31382c1a7c"
            },
            {
                "exclude": "ok",
                "record_id": "bu-FD-F-469",
                "uuid": "e212c0f9-6b16-487f-a4df-4ac402a68210"
            },
            {
                "exclude": "ok",
                "record_id": "bu-FD-F-470",
                "uuid": "4c4cb15d-030c-436a-8d24-2b7d9c38557f"
            },
            {
                "exclude": "ok",
                "record_id": "bu-FD-F-471",
                "uuid": "a29c3368-bfa4-4f29-b388-2aad63a78386"
            },
            {
                "exclude": "ok",
                "record_id": "bu-FD-F-472",
                "uuid": "4e8f2cde-58c0-4063-9f50-027292e9d391"
            },
            {
                "exclude": "ok",
                "record_id": "bu-FD-F-473",
                "uuid": "d6ba530d-4266-4f27-897d-d2ce86f8a8d6"
            },
            {
                "exclude": "ok",
                "record_id": "bu-FD-F-474",
                "uuid": "90d7ea7e-35f7-4aee-8d66-4bcb61efd3b3"
            }
        ],
        "reviewed": true,
        "value": 0.017511623460650876
    },
    "Ar40": {
        "error": 0.019965371655069678,
        "fit": "Bracketing Interpolate",
        "references": [
            {
                "exclude": "ok",
                "record_id": "bu-FD-F-467",
                "uuid": "2a56935c-e9b7-4223-856e-456dd21aefe0"
            },
            {
                "exclude": "ok",
                "record_id": "bu-FD-F-468",
                "uuid": "f67658d0-2729-45a1-8c6b-8b31382c1a7c"
            },
            {
                "exclude": "ok",
                "record_id": "bu-FD-F-469",
                "uuid": "e212c0f9-6b16-487f-a4df-4ac402a68210"
            },
            {
                "exclude": "ok",
                "record_id": "bu-FD-F-470",
                "uuid": "4c4cb15d-030c-436a-8d24-2b7d9c38557f"
            },
            {
                "exclude": "ok",
                "record_id": "bu-FD-F-471",
                "uuid": "a29c3368-bfa4-4f29-b388-2aad63a78386"
            },
            {
                "exclude": "ok",
                "record_id": "bu-FD-F-472",
                "uuid": "4e8f2cde-58c0-4063-9f50-027292e9d391"
            },
            {
                "exclude": "ok",
                "record_id": "bu-FD-F-473",
                "uuid": "d6ba530d-4266-4f27-897d-d2ce86f8a8d6"
            },
            {
                "exclude": "ok",
                "record_id": "bu-FD-F-474",
                "uuid": "90d7ea7e-35f7-4aee-8d66-4bcb61efd3b3"
            }
        ],
        "reviewed": true,
        "value": 0.6823148261499785
    }
}